Workbook

Sheet Dashboard
B2: Founder KPI Dashboard
B3: Live summary — pulls latest month from each KPI sheet. Select reporting month below.
B5: Reporting month (type exactly as column header, e.g. Jun-26): | D5: Jun-26
B7: REVENUE & GROWTH
B9: MRR | D9: ARR | F9: Net new MRR | H9: MRR growth MoM
B10: =INDEX('MRR-ARR'!$C$7:$N$7,MATCH($D$5,'MRR-ARR'!$C$5:$N$5,0)) -> 1470000 | D10: =INDEX('MRR-ARR'!$C$15:$N$15,MATCH($D$5,'MRR-ARR'!$C$5:$N$5,0)) -> 17640000 | F10: =INDEX('MRR-ARR'!$C$12:$N$12,MATCH($D$5,'MRR-ARR'!$C$5:$N$5,0)) -> 1611435 | H10: =INDEX('MRR-ARR'!$C$18:$N$18,MATCH($D$5,'MRR-ARR'!$C$5:$N$5,0)) -> 0.024390244
B12: MRR quick ratio | D12: ARPU | F12: Lead-to-close conv. | H12: Deals closed-won
B13: =INDEX('MRR-ARR'!$C$20:$N$20,MATCH($D$5,'MRR-ARR'!$C$5:$N$5,0)) -> 42.784909 | D13: =INDEX('MRR-ARR'!$C$21:$N$21,MATCH($D$5,'MRR-ARR'!$C$5:$N$5,0)) -> 5000 | F13: =INDEX('Customer Metrics'!$C$28:$N$28,MATCH($D$5,'MRR-ARR'!$C$5:$N$5,0)) -> 0.5 | H13: =INDEX('Customer Metrics'!$C$27:$N$27,MATCH($D$5,'MRR-ARR'!$C$5:$N$5,0)) -> 20
B16: CUSTOMERS
B18: CAC | D18: LTV | F18: LTV : CAC ratio | H18: Logo churn rate
B19: =INDEX('Customer Metrics'!$C$10:$N$10,MATCH($D$5,'MRR-ARR'!$C$5:$N$5,0)) -> 30555.556 | D19: =INDEX('Customer Metrics'!$C$15:$N$15,MATCH($D$5,'MRR-ARR'!$C$5:$N$5,0)) -> 187333.33 | F19: =INDEX('Customer Metrics'!$C$16:$N$16,MATCH($D$5,'MRR-ARR'!$C$5:$N$5,0)) -> 6.1309091 | H19: =INDEX('Customer Metrics'!$C$19:$N$19,MATCH($D$5,'MRR-ARR'!$C$5:$N$5,0)) -> 0.021352313
B21: Net revenue retention | D21: NPS score
B22: =INDEX('Customer Metrics'!$C$20:$N$20,MATCH($D$5,'MRR-ARR'!$C$5:$N$5,0)) -> 1.0418118 | D22: =INDEX('Customer Metrics'!$C$21:$N$21,MATCH($D$5,'MRR-ARR'!$C$5:$N$5,0)) -> 53
B25: BURN & RUNWAY
B27: Monthly net burn | D27: Cash balance | F27: Cash runway (months) | H27: Burn multiple
B28: =INDEX('Burn-Runway'!$C$9:$N$9,MATCH($D$5,'MRR-ARR'!$C$5:$N$5,0)) -> 782454 | D28: =INDEX('Burn-Runway'!$C$12:$N$12,MATCH($D$5,'MRR-ARR'!$C$5:$N$5,0)) -> 17300077 | F28: =INDEX('Burn-Runway'!$C$16:$N$16,MATCH($D$5,'MRR-ARR'!$C$5:$N$5,0)) -> 24.986992 | H28: =INDEX('Burn-Runway'!$C$17:$N$17,MATCH($D$5,'MRR-ARR'!$C$5:$N$5,0)) -> 0.040463624
B31: TEAM & OPS
B33: Headcount | D33: Attrition rate | F33: Revenue per employee
B34: =INDEX('Team-Ops'!$C$7:$N$7,MATCH($D$5,'MRR-ARR'!$C$5:$N$5,0)) -> 15 | D34: =INDEX('Team-Ops'!$C$9:$N$9,MATCH($D$5,'MRR-ARR'!$C$5:$N$5,0)) -> 0 | F34: =INDEX('Team-Ops'!$C$12:$N$12,MATCH($D$5,'MRR-ARR'!$C$5:$N$5,0)) -> 102000
B37: Note: figures pull from the column in each KPI sheet matching the month typed in cell D5.

Sheet Read Me
B2: SaaS Founder KPI Tracker
B3: Placeholder template to compute MRR, ARR, churn, CAC, LTV, burn, runway and team KPIs
B5: How to use this workbook
B6: 1. Enter raw data into the BLUE input cells on the 'Raw Data Input' sheet each month.
B7: 2. Pull P&L, Cash Flow and Balance Sheet figures from Zoho Books Reports API (or manual entry).
B8: 3. Pull Recurring Invoices list from Zoho Books to fill the Customers & Subscriptions table.
B9: 4. All KPI sheets (MRR-ARR, Customer Metrics, Burn-Runway, Team-Ops) calculate automatically.
B10: 5. The Dashboard sheet pulls a live summary from all KPI sheets — do not edit it directly.
B12: Color coding
B13: Blue text = hardcoded input (you type this in)
B14: Black text = formula / calculation (do not overwrite)
B15: Green text = link pulled from another sheet
... B24: Dashboard — one-page summary view, mirrors the founder dashboard

Sheet Raw Data Input
B2: Raw Data Input
B3: Enter monthly figures here. Source noted per section. All values in INR unless noted.
B5: Month | C5: Jan-26 | D5: Feb-26 | E5: Mar-26 | F5: Apr-26 | G5: May-26 | H5: Jun-26 | I5: Jul-26 | J5: Aug-26 | K5: Sep-26 | L5: Oct-26 | M5: Nov-26 | N5: Dec-26
B6: REVENUE & SUBSCRIPTIONS (Source: Zoho Books — Recurring Invoices API)
B7: Active subscriptions (count, end of month) | C7: 260 | D7: 266 | E7: 273 | F7: 280 | G7: 287 | H7: 294 | I7: 302 | J7: 309 | K7: 317 | L7: 325 | M7: 333 | N7: 341
B8: Monthly Subscription Cost | C8: 5000 | D8: 5000 | E8: 5000 | F8: 5000 | G8: 5000 | H8: 5000 | I8: 5000 | J8: 5000 | K8: 5000 | L8: 5000 | M8: 5000 | N8: 5000
B9: Total monthly-normalized invoice value of active subs (Rs) | C9: =C7*C8 -> 1300000 | D9: =D7*D8 -> 1330000 | E9: =E7*E8 -> 1365000 | F9: =F7*F8 -> 1400000 | G9: =G7*G8 -> 1435000 | H9: =H7*H8 -> 1470000 | I9: =I7*I8 -> 1510000 | J9: =J7*J8 -> 1545000 | ... N9: =N7*N8 -> 1705000
B10: New subscriptions started this month (count) | C10: 16 | D10: 16 | E10: 16 | F10: 17 | G10: 17 | H10: 18 | I10: 18 | J10: 19 | K10: 19 | L10: 20 | M10: 20 | N10: 20
B11: New MRR added this month (Rs) | C11: =C9+C10*C8 -> 1380000 | D11: =D9+D10*D8 -> 1410000 | E11: =E9+E10*E8 -> 1445000 | F11: =F9+F10*F8 -> 1485000 | G11: =G9+G10*G8 -> 1520000 | H11: =H9+H10*H8 -> 1560000 | I11: =I9+I10*I8 -> 1600000 | J11: =J9+J10*J8 -> 1640000 | ... N11: =N9+N10*N8 -> 1805000
B12: Subscriptions upgraded this month — MRR added (Rs) | C12: =C11-C9 -> 80000 | D12: =D11-D9 -> 80000 | E12: =E11-E9 -> 80000 | F12: =F11-F9 -> 85000 | G12: =G11-G9 -> 85000 | H12: =H11-H9 -> 90000 | I12: =I11-I9 -> 90000 | J12: =J11-J9 -> 95000 | ... N12: =N11-N9 -> 100000
B13: Subscriptions downgraded this month — MRR lost (Rs) | C13: 6400 | D13: 6784 | E13: 7191 | F13: 7622 | G13: 8080 | H13: 8565 | I13: 9079 | J13: 9623 | K13: 10201 | L13: 10813 | M13: 11461 | N13: 12149
B14: Subscriptions cancelled this month (count) | C14: 5 | D14: 5 | E14: 5 | F14: 6 | G14: 6 | H14: 6 | I14: 6 | J14: 6 | K14: 6 | L14: 6 | M14: 7 | N14: 7
B15: MRR lost to cancellations this month (Rs) | C15: =C8*C14 -> 25000 | D15: =D8*D14 -> 25000 | E15: =E8*E14 -> 25000 | F15: =F8*F14 -> 30000 | G15: =G8*G14 -> 30000 | H15: =H8*H14 -> 30000 | I15: =I8*I14 -> 30000 | J15: =J8*J14 -> 30000 | ... N15: =N8*N14 -> 35000
B17: P&L / CASH FLOW (Source: Zoho Books — /reports/profitandloss, /reports/cashflow)
B18: Total revenue recognized this month (Rs) — from P&L Operating Income | C18: =C11-C15 -> 1355000 | D18: =D11-D15 -> 1385000 | E18: =E11-E15 -> 1420000 | F18: =F11-F15 -> 1455000 | G18: =G11-G15 -> 1490000 | H18: =H11-H15 -> 1530000 | I18: =I11-I15 -> 1570000 | J18: =J11-J15 -> 1610000 | ... N18: =N11-N15 -> 1770000
B19: Total operating expenses this month (Rs) — from P&L | C19: 1728000 | D19: 1831680 | E19: 1941581 | F19: 2058075 | G19: 2181561 | H19: 2312454 | I19: 2451200 | J19: 2598273 | K19: 2754170 | L19: 2919420 | M19: 3094585 | N19: 3280260
B20: Cash & bank balance, end of month (Rs) — from Balance Sheet | C20: 20539200 | D20: 20023104 | E20: 19446736 | F20: 18804720 | G20: 18091250 | H20: 17300077 | I20: 16424430 | J20: 15457022 | K20: 14389995 | L20: 13214874 | M20: 11922551 | N20: 10503167
B22: CUSTOMERS & SALES (Source: Zoho CRM / Zoho Books Contacts)
B23: Total active customers, end of month (count) | C23: 260 | D23: 266 | E23: =E7-E14 -> 268 | F23: =F7-F14 -> 274 | G23: =G7-G14 -> 281 | H23: =H7-H14 -> 288 | I23: =I7-I14 -> 296 | J23: =J7-J14 -> 303 | K23: =K7-K14 -> 311 | L23: =L7-L14 -> 319 | ... N23: =N7-N14 -> 334
B24: New customers acquired this month (count) | C24: 16 | D24: 16 | E24: =E10 -> 16 | F24: =F10 -> 17 | G24: =G10 -> 17 | H24: =H10 -> 18 | I24: =I10 -> 18 | J24: =J10 -> 19 | K24: =K10 -> 19 | L24: =L10 -> 20 | ... N24: =N10 -> 20
B25: Customers churned this month (count) | C25: 5 | D25: 5 | E25: =E14 -> 5 | F25: =F14 -> 6 | G25: =G14 -> 6 | H25: =H14 -> 6 | I25: =I14 -> 6 | J25: =J14 -> 6 | K25: =K14 -> 6 | L25: =L14 -> 6 | ... N25: =N14 -> 7
B26: Sales & marketing spend this month (Rs) | C26: 448000 | D26: 448000 | E26: 500000 | F26: 550000 | G26: 550000 | H26: 550000 | I26: 550000 | J26: 550000 | K26: 550000 | L26: 550000 | M26: 550000 | N26: 550000
B27: Leads generated this month (count) | C27: 176 | D27: 176 | E27: 20 | F27: 30 | G27: 30 | H27: 40 | I27: 10 | J27: 20 | K27: 30 | L27: 40 | M27: 10 | N27: 20
B28: Leads qualified this month (count) | C28: 109 | D28: 109 | E28: 5 | F28: 10 | G28: 15 | H28: 20 | I28: 10 | J28: 15 | K28: 10 | L28: 10 | M28: 10 | N28: 10
B29: Demos completed this month (count) | C29: 59 | D29: 59 | E29: 5 | F29: 10 | G29: 15 | H29: 20 | I29: 10 | J29: 0 | K29: 10 | L29: 0 | M29: 10 | N29: 10
B30: Deals closed-won this month (count) | C30: 16 | D30: 16 | E30: 5 | F30: 10 | G30: 15 | H30: 20 | I30: 10 | J30: 0 | K30: 10 | L30: 0 | M30: 10 | N30: 10
B31: NPS score this month (survey tool, -100 to 100) | C31: 52 | D31: 53 | E31: 54 | F31: 55 | G31: 52 | H31: 53 | I31: 54 | J31: 55 | K31: 52 | L31: 53 | M31: 54 | N31: 55
B33: TEAM & OPS (Source: Zoho People / Payroll)
B34: Headcount, end of month | C34: 36 | D34: 37 | E34: 10 | F34: 10 | G34: 15 | H34: 15 | I34: 15 | J34: 15 | K34: 15 | L34: 15 | M34: 15 | N34: 15
B35: Employees exited this month (count) | C35: 1 | D35: 0 | E35: 0 | F35: 1 | G35: 0 | H35: 0 | I35: 1 | J35: 0 | K35: 0 | L35: 1 | M35: 0 | N35: 0
B36: Open roles (count) | C36: 5 | D36: 5 | E36: 5 | F36: 5 | G36: 5 | H36: 5 | I36: 4 | J36: 4 | K36: 4 | L36: 4 | M36: 4 | N36: 4

Sheet MRR-ARR
B2: MRR & ARR
B3: All cells link to 'Raw Data Input'. Formulas only — do not hardcode values here.
B5: Month | C5: Jan-26 | D5: Feb-26 | E5: Mar-26 | F5: Apr-26 | G5: May-26 | H5: Jun-26 | I5: Jul-26 | J5: Aug-26 | K5: Sep-26 | L5: Oct-26 | M5: Nov-26 | N5: Dec-26
B6: MONTHLY RECURRING REVENUE
B7: MRR — total active normalized monthly value (Rs) | C7: ='Raw Data Input'!C9 -> 1300000 | D7: ='Raw Data Input'!D9 -> 1330000 | E7: ='Raw Data Input'!E9 -> 1365000 | F7: ='Raw Data Input'!F9 -> 1400000 | G7: ='Raw Data Input'!G9 -> 1435000 | H7: ='Raw Data Input'!H9 -> 1470000 | I7: ='Raw Data Input'!I9 -> 1510000 | J7: ='Raw Data Input'!J9 -> 1545000 | ... N7: ='Raw Data Input'!N9 -> 1705000
B8: New MRR added | C8: ='Raw Data Input'!C11 -> 1380000 | D8: ='Raw Data Input'!D11 -> 1410000 | E8: ='Raw Data Input'!E11 -> 1445000 | F8: ='Raw Data Input'!F11 -> 1485000 | G8: ='Raw Data Input'!G11 -> 1520000 | H8: ='Raw Data Input'!H11 -> 1560000 | I8: ='Raw Data Input'!I11 -> 1600000 | J8: ='Raw Data Input'!J11 -> 1640000 | ... N8: ='Raw Data Input'!N11 -> 1805000
B9: Expansion MRR (upgrades) | C9: ='Raw Data Input'!C12 -> 80000 | D9: ='Raw Data Input'!D12 -> 80000 | E9: ='Raw Data Input'!E12 -> 80000 | F9: ='Raw Data Input'!F12 -> 85000 | G9: ='Raw Data Input'!G12 -> 85000 | H9: ='Raw Data Input'!H12 -> 90000 | I9: ='Raw Data Input'!I12 -> 90000 | J9: ='Raw Data Input'!J12 -> 95000 | ... N9: ='Raw Data Input'!N12 -> 100000
B10: Contraction MRR (downgrades) | C10: =-'Raw Data Input'!C13 -> -6400 | D10: =-'Raw Data Input'!D13 -> -6784 | E10: =-'Raw Data Input'!E13 -> -7191 | F10: =-'Raw Data Input'!F13 -> -7622 | G10: =-'Raw Data Input'!G13 -> -8080 | H10: =-'Raw Data Input'!H13 -> -8565 | I10: =-'Raw Data Input'!I13 -> -9079 | J10: =-'Raw Data Input'!J13 -> -9623 | ... N10: =-'Raw Data Input'!N13 -> -12149
B11: Churned MRR (cancellations) | C11: =-'Raw Data Input'!C15 -> -25000 | D11: =-'Raw Data Input'!D15 -> -25000 | E11: =-'Raw Data Input'!E15 -> -25000 | F11: =-'Raw Data Input'!F15 -> -30000 | G11: =-'Raw Data Input'!G15 -> -30000 | H11: =-'Raw Data Input'!H15 -> -30000 | I11: =-'Raw Data Input'!I15 -> -30000 | J11: =-'Raw Data Input'!J15 -> -30000 | ... N11: =-'Raw Data Input'!N15 -> -35000
B12: Net new MRR (new + expansion - contraction - churn) | C12: =SUM(C8:C11) -> 1428600 | D12: =SUM(D8:D11) -> 1458216 | E12: =SUM(E8:E11) -> 1492809 | F12: =SUM(F8:F11) -> 1532378 | G12: =SUM(G8:G11) -> 1566920 | H12: =SUM(H8:H11) -> 1611435 | I12: =SUM(I8:I11) -> 1650921 | J12: =SUM(J8:J11) -> 1695377 | ... N12: =SUM(N8:N11) -> 1857851
B14: ANNUAL RECURRING REVENUE
B15: ARR (MRR x 12) | C15: =C7*12 -> 15600000 | D15: =D7*12 -> 15960000 | E15: =E7*12 -> 16380000 | F15: =F7*12 -> 16800000 | G15: =G7*12 -> 17220000 | H15: =H7*12 -> 17640000 | I15: =I7*12 -> 18120000 | J15: =J7*12 -> 18540000 | ... N15: =N7*12 -> 20460000
B17: GROWTH METRICS
B18: MRR growth rate MoM (%) | C18: ="n/a" -> n/a | D18: =IFERROR((D7-C7)/C7,0) -> 0.023076923 | E18: =IFERROR((E7-D7)/D7,0) -> 0.026315789 | F18: =IFERROR((F7-E7)/E7,0) -> 0.025641026 | G18: =IFERROR((G7-F7)/F7,0) -> 0.025 | H18: =IFERROR((H7-G7)/G7,0) -> 0.024390244 | I18: =IFERROR((I7-H7)/H7,0) -> 0.027210884 | J18: =IFERROR((J7-I7)/I7,0) -> 0.023178808 | K18: =IFERROR((K7-J7)/J7,0) -> 0.025889968 | ... N18: =IFERROR((N7-M7)/M7,0) -> 0.024024024
B19: MRR churn rate (%) = churned MRR / prior month MRR | C19: ="n/a" -> n/a | D19: =IFERROR('Raw Data Input'!D15/C7,0) -> 0.019230769 | E19: =IFERROR('Raw Data Input'!E15/D7,0) -> 0.018796992 | F19: =IFERROR('Raw Data Input'!F15/E7,0) -> 0.021978022 | G19: =IFERROR('Raw Data Input'!G15/F7,0) -> 0.021428571 | H19: =IFERROR('Raw Data Input'!H15/G7,0) -> 0.020905923 | I19: =IFERROR('Raw Data Input'!I15/H7,0) -> 0.020408163 | J19: =IFERROR('Raw Data Input'!J15/I7,0) -> 0.01986755 | K19: =IFERROR('Raw Data Input'!K15/J7,0) -> 0.019417476 | ... N19: =IFERROR('Raw Data Input'!N15/M7,0) -> 0.021021021
B20: MRR quick ratio = (new + expansion) / (contraction + churn) | C20: =IFERROR(('Raw Data Input'!C11+'Raw Data Input'!C12)/('Raw Data Input'!C13+'Raw Data Input'!C15),0) -> 46.496815 | D20: =IFERROR(('Raw Data Input'!D11+'Raw Data Input'!D12)/('Raw Data Input'!D13+'Raw Data Input'!D15),0) -> 46.878933 | E20: =IFERROR(('Raw Data Input'!E11+'Raw Data Input'!E12)/('Raw Data Input'!E13+'Raw Data Input'!E15),0) -> 47.373489 | F20: =IFERROR(('Raw Data Input'!F11+'Raw Data Input'!F12)/('Raw Data Input'!F13+'Raw Data Input'!F15),0) -> 41.730902 | G20: =IFERROR(('Raw Data Input'!G11+'Raw Data Input'!G12)/('Raw Data Input'!G13+'Raw Data Input'!G15),0) -> 42.148109 | H20: =IFERROR(('Raw Data Input'!H11+'Raw Data Input'!H12)/('Raw Data Input'!H13+'Raw Data Input'!H15),0) -> 42.784909 | I20: =IFERROR(('Raw Data Input'!I11+'Raw Data Input'!I12)/('Raw Data Input'!I13+'Raw Data Input'!I15),0) -> 43.245733 | J20: =IFERROR(('Raw Data Input'!J11+'Raw Data Input'!J12)/('Raw Data Input'!J13+'Raw Data Input'!J15),0) -> 43.787699 | ... N20: =IFERROR(('Raw Data Input'!N11+'Raw Data Input'!N12)/('Raw Data Input'!N13+'Raw Data Input'!N15),0) -> 40.403826
B21: ARPU = MRR / active subscriptions | C21: =IFERROR(C7/'Raw Data Input'!C7,0) -> 5000 | D21: =IFERROR(D7/'Raw Data Input'!D7,0) -> 5000 | E21: =IFERROR(E7/'Raw Data Input'!E7,0) -> 5000 | F21: =IFERROR(F7/'Raw Data Input'!F7,0) -> 5000 | G21: =IFERROR(G7/'Raw Data Input'!G7,0) -> 5000 | H21: =IFERROR(H7/'Raw Data Input'!H7,0) -> 5000 | I21: =IFERROR(I7/'Raw Data Input'!I7,0) -> 5000 | J21: =IFERROR(J7/'Raw Data Input'!J7,0) -> 5000 | ... N21: =IFERROR(N7/'Raw Data Input'!N7,0) -> 5000

Sheet Customer Metrics
B2: Customer Metrics
B3: CAC, LTV, churn, NRR, NPS and sales funnel — linked from Raw Data Input.
B5: Month | C5: Jan-26 | D5: Feb-26 | E5: Mar-26 | F5: Apr-26 | G5: May-26 | H5: Jun-26 | I5: Jul-26 | J5: Aug-26 | K5: Sep-26 | L5: Oct-26 | M5: Nov-26 | N5: Dec-26
B6: ASSUMPTIONS
B7: Gross margin assumption (%) — used in LTV calc | C7: 0.8 | D7: 0.8 | E7: 0.8 | F7: 0.8 | G7: 0.8 | H7: 0.8 | I7: 0.8 | J7: 0.8 | K7: 0.8 | L7: 0.8 | M7: 0.8 | N7: 0.8
B9: CUSTOMER ACQUISITION COST (CAC)
B10: CAC = sales & marketing spend / new customers acquired | C10: =IFERROR('Raw Data Input'!C26/'Raw Data Input'!C24,0) -> 28000 | D10: =IFERROR('Raw Data Input'!D26/'Raw Data Input'!D24,0) -> 28000 | E10: =IFERROR('Raw Data Input'!E26/'Raw Data Input'!E24,0) -> 31250 | F10: =IFERROR('Raw Data Input'!F26/'Raw Data Input'!F24,0) -> 32352.941 | G10: =IFERROR('Raw Data Input'!G26/'Raw Data Input'!G24,0) -> 32352.941 | H10: =IFERROR('Raw Data Input'!H26/'Raw Data Input'!H24,0) -> 30555.556 | I10: =IFERROR('Raw Data Input'!I26/'Raw Data Input'!I24,0) -> 30555.556 | J10: =IFERROR('Raw Data Input'!J26/'Raw Data Input'!J24,0) -> 28947.368 | ... N10: =IFERROR('Raw Data Input'!N26/'Raw Data Input'!N24,0) -> 27500
B12: CUSTOMER LIFETIME VALUE (LTV)
B13: Customer churn rate (%) = churned customers / active customers (start of month) | C13: ="n/a" -> n/a | D13: =IFERROR('Raw Data Input'!D25/'Raw Data Input'!C23,0) -> 0.019230769 | E13: =IFERROR('Raw Data Input'!E25/'Raw Data Input'!D23,0) -> 0.018796992 | F13: =IFERROR('Raw Data Input'!F25/'Raw Data Input'!E23,0) -> 0.02238806 | G13: =IFERROR('Raw Data Input'!G25/'Raw Data Input'!F23,0) -> 0.02189781 | H13: =IFERROR('Raw Data Input'!H25/'Raw Data Input'!G23,0) -> 0.021352313 | I13: =IFERROR('Raw Data Input'!I25/'Raw Data Input'!H23,0) -> 0.020833333 | J13: =IFERROR('Raw Data Input'!J25/'Raw Data Input'!I23,0) -> 0.02027027 | K13: =IFERROR('Raw Data Input'!K25/'Raw Data Input'!J23,0) -> 0.01980198 | ... N13: =IFERROR('Raw Data Input'!N25/'Raw Data Input'!M23,0) -> 0.021472393
B14: ARPU (linked from MRR-ARR sheet) | C14: ='MRR-ARR'!C21 -> 5000 | D14: ='MRR-ARR'!D21 -> 5000 | E14: ='MRR-ARR'!E21 -> 5000 | F14: ='MRR-ARR'!F21 -> 5000 | G14: ='MRR-ARR'!G21 -> 5000 | H14: ='MRR-ARR'!H21 -> 5000 | I14: ='MRR-ARR'!I21 -> 5000 | J14: ='MRR-ARR'!J21 -> 5000 | ... N14: ='MRR-ARR'!N21 -> 5000
B15: LTV = (ARPU x gross margin) / customer churn rate | C15: ="n/a" -> n/a | D15: =IFERROR((D14*D7)/D13,0) -> 208000 | E15: =IFERROR((E14*E7)/E13,0) -> 212800 | F15: =IFERROR((F14*F7)/F13,0) -> 178666.67 | G15: =IFERROR((G14*G7)/G13,0) -> 182666.67 | H15: =IFERROR((H14*H7)/H13,0) -> 187333.33 | I15: =IFERROR((I14*I7)/I13,0) -> 192000 | J15: =IFERROR((J14*J7)/J13,0) -> 197333.33 | K15: =IFERROR((K14*K7)/K13,0) -> 202000 | ... N15: =IFERROR((N14*N7)/N13,0) -> 186285.71
B16: LTV : CAC ratio | C16: ="n/a" -> n/a | D16: =IFERROR(D15/D10,0) -> 7.4285714 | E16: =IFERROR(E15/E10,0) -> 6.8096 | F16: =IFERROR(F15/F10,0) -> 5.5224242 | G16: =IFERROR(G15/G10,0) -> 5.6460606 | H16: =IFERROR(H15/H10,0) -> 6.1309091 | I16: =IFERROR(I15/I10,0) -> 6.2836364 | J16: =IFERROR(J15/J10,0) -> 6.8169697 | K16: =IFERROR(K15/K10,0) -> 6.9781818 | ... N16: =IFERROR(N15/N10,0) -> 6.774026
B18: RETENTION & SATISFACTION
B19: Logo churn rate (%) (same as customer churn above) | C19: =C13 -> n/a | D19: =D13 -> 0.019230769 | E19: =E13 -> 0.018796992 | F19: =F13 -> 0.02238806 | G19: =G13 -> 0.02189781 | H19: =H13 -> 0.021352313 | I19: =I13 -> 0.020833333 | J19: =J13 -> 0.02027027 | ... N19: =N13 -> 0.021472393
B20: Net revenue retention (%) = 1 - MRR churn rate + expansion rate | C20: ="n/a" -> n/a | D20: =IFERROR(1-'MRR-ARR'!D19+'Raw Data Input'!D12/'Raw Data Input'!C9,0) -> 1.0423077 | E20: =IFERROR(1-'MRR-ARR'!E19+'Raw Data Input'!E12/'Raw Data Input'!D9,0) -> 1.0413534 | F20: =IFERROR(1-'MRR-ARR'!F19+'Raw Data Input'!F12/'Raw Data Input'!E9,0) -> 1.040293 | G20: =IFERROR(1-'MRR-ARR'!G19+'Raw Data Input'!G12/'Raw Data Input'!F9,0) -> 1.0392857 | H20: =IFERROR(1-'MRR-ARR'!H19+'Raw Data Input'!H12/'Raw Data Input'!G9,0) -> 1.0418118 | I20: =IFERROR(1-'MRR-ARR'!I19+'Raw Data Input'!I12/'Raw Data Input'!H9,0) -> 1.0408163 | J20: =IFERROR(1-'MRR-ARR'!J19+'Raw Data Input'!J12/'Raw Data Input'!I9,0) -> 1.0430464 | K20: =IFERROR(1-'MRR-ARR'!K19+'Raw Data Input'!K12/'Raw Data Input'!J9,0) -> 1.0420712 | ... N20: =IFERROR(1-'MRR-ARR'!N19+'Raw Data Input'!N12/'Raw Data Input'!M9,0) -> 1.039039
B21: NPS score (linked from Raw Data Input) | C21: ='Raw Data Input'!C31 -> 52 | D21: ='Raw Data Input'!D31 -> 53 | E21: ='Raw Data Input'!E31 -> 54 | F21: ='Raw Data Input'!F31 -> 55 | G21: ='Raw Data Input'!G31 -> 52 | H21: ='Raw Data Input'!H31 -> 53 | I21: ='Raw Data Input'!I31 -> 54 | J21: ='Raw Data Input'!J31 -> 55 | ... N21: ='Raw Data Input'!N31 -> 55
B23: SALES FUNNEL & CONVERSION
B24: Leads generated | C24: ='Raw Data Input'!C27 -> 176 | D24: ='Raw Data Input'!D27 -> 176 | E24: ='Raw Data Input'!E27 -> 20 | F24: ='Raw Data Input'!F27 -> 30 | G24: ='Raw Data Input'!G27 -> 30 | H24: ='Raw Data Input'!H27 -> 40 | I24: ='Raw Data Input'!I27 -> 10 | J24: ='Raw Data Input'!J27 -> 20 | ... N24: ='Raw Data Input'!N27 -> 20
B25: Leads qualified | C25: ='Raw Data Input'!C28 -> 109 | D25: ='Raw Data Input'!D28 -> 109 | E25: ='Raw Data Input'!E28 -> 5 | F25: ='Raw Data Input'!F28 -> 10 | G25: ='Raw Data Input'!G28 -> 15 | H25: ='Raw Data Input'!H28 -> 20 | I25: ='Raw Data Input'!I28 -> 10 | J25: ='Raw Data Input'!J28 -> 15 | ... N25: ='Raw Data Input'!N28 -> 10
B26: Demos completed | C26: ='Raw Data Input'!C29 -> 59 | D26: ='Raw Data Input'!D29 -> 59 | E26: ='Raw Data Input'!E29 -> 5 | F26: ='Raw Data Input'!F29 -> 10 | G26: ='Raw Data Input'!G29 -> 15 | H26: ='Raw Data Input'!H29 -> 20 | I26: ='Raw Data Input'!I29 -> 10 | J26: ='Raw Data Input'!J29 -> 0 | ... N26: ='Raw Data Input'!N29 -> 10
B27: Deals closed-won | C27: ='Raw Data Input'!C30 -> 16 | D27: ='Raw Data Input'!D30 -> 16 | E27: ='Raw Data Input'!E30 -> 5 | F27: ='Raw Data Input'!F30 -> 10 | G27: ='Raw Data Input'!G30 -> 15 | H27: ='Raw Data Input'!H30 -> 20 | I27: ='Raw Data Input'!I30 -> 10 | J27: ='Raw Data Input'!J30 -> 0 | ... N27: ='Raw Data Input'!N30 -> 10
B28: Lead-to-close conversion rate (%) | C28: =IFERROR('Raw Data Input'!C30/'Raw Data Input'!C27,0) -> 0.090909091 | D28: =IFERROR('Raw Data Input'!D30/'Raw Data Input'!D27,0) -> 0.090909091 | E28: =IFERROR('Raw Data Input'!E30/'Raw Data Input'!E27,0) -> 0.25 | F28: =IFERROR('Raw Data Input'!F30/'Raw Data Input'!F27,0) -> 0.33333333 | G28: =IFERROR('Raw Data Input'!G30/'Raw Data Input'!G27,0) -> 0.5 | H28: =IFERROR('Raw Data Input'!H30/'Raw Data Input'!H27,0) -> 0.5 | I28: =IFERROR('Raw Data Input'!I30/'Raw Data Input'!I27,0) -> 1 | J28: =IFERROR('Raw Data Input'!J30/'Raw Data Input'!J27,0) -> 0 | ... N28: =IFERROR('Raw Data Input'!N30/'Raw Data Input'!N27,0) -> 0.5

Sheet Burn-Runway
B2: Burn & Runway
B3: Linked from Raw Data Input (Zoho Books P&L / Balance Sheet).
B5: Month | C5: Jan-26 | D5: Feb-26 | E5: Mar-26 | F5: Apr-26 | G5: May-26 | H5: Jun-26 | I5: Jul-26 | J5: Aug-26 | K5: Sep-26 | L5: Oct-26 | M5: Nov-26 | N5: Dec-26
B6: MONTHLY BURN
B7: Revenue recognized this month | C7: ='Raw Data Input'!C18 -> 1355000 | D7: ='Raw Data Input'!D18 -> 1385000 | E7: ='Raw Data Input'!E18 -> 1420000 | F7: ='Raw Data Input'!F18 -> 1455000 | G7: ='Raw Data Input'!G18 -> 1490000 | H7: ='Raw Data Input'!H18 -> 1530000 | I7: ='Raw Data Input'!I18 -> 1570000 | J7: ='Raw Data Input'!J18 -> 1610000 | ... N7: ='Raw Data Input'!N18 -> 1770000
B8: Operating expenses this month | C8: ='Raw Data Input'!C19 -> 1728000 | D8: ='Raw Data Input'!D19 -> 1831680 | E8: ='Raw Data Input'!E19 -> 1941581 | F8: ='Raw Data Input'!F19 -> 2058075 | G8: ='Raw Data Input'!G19 -> 2181561 | H8: ='Raw Data Input'!H19 -> 2312454 | I8: ='Raw Data Input'!I19 -> 2451200 | J8: ='Raw Data Input'!J19 -> 2598273 | ... N8: ='Raw Data Input'!N19 -> 3280260
B9: Net burn = operating expenses - revenue | C9: =C8-C7 -> 373000 | D9: =D8-D7 -> 446680 | E9: =E8-E7 -> 521581 | F9: =F8-F7 -> 603075 | G9: =G8-G7 -> 691561 | H9: =H8-H7 -> 782454 | I9: =I8-I7 -> 881200 | J9: =J8-J7 -> 988273 | ... N9: =N8-N7 -> 1510260
B11: CASH POSITION
B12: Cash & bank balance, end of month | C12: ='Raw Data Input'!C20 -> 20539200 | D12: ='Raw Data Input'!D20 -> 20023104 | E12: ='Raw Data Input'!E20 -> 19446736 | F12: ='Raw Data Input'!F20 -> 18804720 | G12: ='Raw Data Input'!G20 -> 18091250 | H12: ='Raw Data Input'!H20 -> 17300077 | I12: ='Raw Data Input'!I20 -> 16424430 | J12: ='Raw Data Input'!J20 -> 15457022 | ... N12: ='Raw Data Input'!N20 -> 10503167
B13: Trailing 3-month average burn | C13: =AVERAGE(C9:C9) -> 373000 | D13: =AVERAGE(C9:D9) -> 409840 | E13: =AVERAGE(C9:E9) -> 447087 | F13: =AVERAGE(D9:F9) -> 523778.67 | G13: =AVERAGE(E9:G9) -> 605405.67 | H13: =AVERAGE(F9:H9) -> 692363.33 | I13: =AVERAGE(G9:I9) -> 785071.67 | J13: =AVERAGE(H9:J9) -> 883975.67 | K13: =AVERAGE(I9:K9) -> 991214.33 | L13: =AVERAGE(J9:L9) -> 1105621 | ... N13: =AVERAGE(L9:N9) -> 1366421.7
B15: RUNWAY & EFFICIENCY
B16: Cash runway (months) = cash balance / trailing 3-mo avg burn | C16: =IFERROR(C12/C13,0) -> 55.064879 | D16: =IFERROR(D12/D13,0) -> 48.855905 | E16: =IFERROR(E12/E13,0) -> 43.496536 | F16: =IFERROR(F12/F13,0) -> 35.902035 | G16: =IFERROR(G12/G13,0) -> 29.882855 | H16: =IFERROR(H12/H13,0) -> 24.986992 | I16: =IFERROR(I12/I13,0) -> 20.920931 | J16: =IFERROR(J12/J13,0) -> 17.4858 | ... N16: =IFERROR(N12/N13,0) -> 7.6866221
B17: Burn multiple = net burn / net new ARR | C17: =IFERROR(C9/('MRR-ARR'!C12*12),0) -> 0.021757898 | D17: =IFERROR(D9/('MRR-ARR'!D12*12),0) -> 0.025526625 | E17: =IFERROR(E9/('MRR-ARR'!E12*12),0) -> 0.029116306 | F17: =IFERROR(F9/('MRR-ARR'!F12*12),0) -> 0.032796249 | G17: =IFERROR(G9/('MRR-ARR'!G12*12),0) -> 0.036779212 | H17: =IFERROR(H9/('MRR-ARR'!H12*12),0) -> 0.040463624 | I17: =IFERROR(I9/('MRR-ARR'!I12*12),0) -> 0.044480222 | J17: =IFERROR(J9/('MRR-ARR'!J12*12),0) -> 0.048576855 | ... N17: =IFERROR(N9/('MRR-ARR'!N12*12),0) -> 0.067742246

Sheet Team-Ops
B2: Team & Ops
B3: Linked from Raw Data Input (Zoho People / Payroll) and MRR-ARR sheet.
B5: Month | C5: Jan-26 | D5: Feb-26 | E5: Mar-26 | F5: Apr-26 | G5: May-26 | H5: Jun-26 | I5: Jul-26 | J5: Aug-26 | K5: Sep-26 | L5: Oct-26 | M5: Nov-26 | N5: Dec-26
B6: HEADCOUNT
B7: Headcount, end of month | C7: ='Raw Data Input'!C34 -> 36 | D7: ='Raw Data Input'!D34 -> 37 | E7: ='Raw Data Input'!E34 -> 10 | F7: ='Raw Data Input'!F34 -> 10 | G7: ='Raw Data Input'!G34 -> 15 | H7: ='Raw Data Input'!H34 -> 15 | I7: ='Raw Data Input'!I34 -> 15 | J7: ='Raw Data Input'!J34 -> 15 | ... N7: ='Raw Data Input'!N34 -> 15
B8: Open roles | C8: ='Raw Data Input'!C36 -> 5 | D8: ='Raw Data Input'!D36 -> 5 | E8: ='Raw Data Input'!E36 -> 5 | F8: ='Raw Data Input'!F36 -> 5 | G8: ='Raw Data Input'!G36 -> 5 | H8: ='Raw Data Input'!H36 -> 5 | I8: ='Raw Data Input'!I36 -> 4 | J8: ='Raw Data Input'!J36 -> 4 | ... N8: ='Raw Data Input'!N36 -> 4
B9: Attrition rate (%) = exits this month / headcount (start of month) | C9: ="n/a" -> n/a | D9: =IFERROR('Raw Data Input'!D35/'Raw Data Input'!C34,0) -> 0 | E9: =IFERROR('Raw Data Input'!E35/'Raw Data Input'!D34,0) -> 0 | F9: =IFERROR('Raw Data Input'!F35/'Raw Data Input'!E34,0) -> 0.1 | G9: =IFERROR('Raw Data Input'!G35/'Raw Data Input'!F34,0) -> 0 | H9: =IFERROR('Raw Data Input'!H35/'Raw Data Input'!G34,0) -> 0 | I9: =IFERROR('Raw Data Input'!I35/'Raw Data Input'!H34,0) -> 0.066666667 | J9: =IFERROR('Raw Data Input'!J35/'Raw Data Input'!I34,0) -> 0 | K9: =IFERROR('Raw Data Input'!K35/'Raw Data Input'!J34,0) -> 0 | ... N9: =IFERROR('Raw Data Input'!N35/'Raw Data Input'!M34,0) -> 0
B11: PRODUCTIVITY
B12: Revenue per employee = monthly revenue / headcount | C12: =IFERROR('Raw Data Input'!C18/C7,0) -> 37638.889 | D12: =IFERROR('Raw Data Input'!D18/D7,0) -> 37432.432 | E12: =IFERROR('Raw Data Input'!E18/E7,0) -> 142000 | F12: =IFERROR('Raw Data Input'!F18/F7,0) -> 145500 | G12: =IFERROR('Raw Data Input'!G18/G7,0) -> 99333.333 | H12: =IFERROR('Raw Data Input'!H18/H7,0) -> 102000 | I12: =IFERROR('Raw Data Input'!I18/I7,0) -> 104666.67 | J12: =IFERROR('Raw Data Input'!J18/J7,0) -> 107333.33 | ... N12: =IFERROR('Raw Data Input'!N18/N7,0) -> 118000
B13: MRR per employee = MRR / headcount | C13: =IFERROR('MRR-ARR'!C7/C7,0) -> 36111.111 | D13: =IFERROR('MRR-ARR'!D7/D7,0) -> 35945.946 | E13: =IFERROR('MRR-ARR'!E7/E7,0) -> 136500 | F13: =IFERROR('MRR-ARR'!F7/F7,0) -> 140000 | G13: =IFERROR('MRR-ARR'!G7/G7,0) -> 95666.667 | H13: =IFERROR('MRR-ARR'!H7/H7,0) -> 98000 | I13: =IFERROR('MRR-ARR'!I7/I7,0) -> 100666.67 | J13: =IFERROR('MRR-ARR'!J7/J7,0) -> 103000 | ... N13: =IFERROR('MRR-ARR'!N7/N7,0) -> 113666.67
